{
  "agent": {
    "fullName": "루시아 엘로웬",
    "shortName": "엘로웬",
    "attr": "에테르",
    "cls": "지원",
    "faction": "등장하는 괴담방",
    "grade": "S",
    "version": ""
  },
  "skills": [
    {
      "name": "일반공격: 별 궤적 콤보",
      "major": "일반 공격",
      "minor": "일반공격",
      "description": "별 궤적 콤보\n을 짧게 탭하여 시전:전방으로 최대 5단의 타격을 가하여 에테르 피해를 준다.이때 5번째 공격은 [단상]으로, 시전 시 에테리얼 형상을 재현해 전방 원형 구역의 적에게 에테르 피해를 준다.교전 상태이며 [꿈세계] 상태가 아닐 때, 루시아가 이 [단상]을 시전하면 [꿈세계 게이지] 40pt를 획득한다.\n1단 / 2단 / 3단 / 4단 / 구상 / 합창 / 여진 피해 배율\n1단 / 2단 / 3단 / 4단 / 구상 / 합창 / 여진 그로기 배율"
    },
    {
      "name": "회피: 그림자 끌기",
      "major": "회피스킬",
      "minor": "회피",
      "description": "그림자 끌기\n을 짧게 탭하여 시전:빠른 대시로 회피한다.스킬을 시전하는 동안 무적 효과를 보유한다.\n그림자 끌기"
    },
    {
      "name": "대시공격: 굴절",
      "major": "회피스킬",
      "minor": "대시공격",
      "description": "굴절\n회피 시 을 짧게 탭하여 시전:전방을 빠르게 타격해 에테르 피해를 준다.\n<img class='V0NZnDRF' width='100%' src='//i.namu.wiki/i/sCvfX"
    },
    {
      "name": "회피반격: 스타더스트 에코",
      "major": "회피스킬",
      "minor": "회피반격",
      "description": "스타더스트 에코\n[극한 회피] 발동 후 을 짧게 탭하여 시전:회피 반격은 [단상]에테르 피해를 준다.[꿈세계] 상태가 아닐 때 루시아가 이 [단상]을 시전하면 [꿈세계 게이지] 20pt를 획득한다. 5초 동안 최대 1회 획득 가능하다.스킬을 시전하는 동안 무적 효과를 보유한다.\n구상 / 합창 피해 배율\n구상 / 합창 그로기 배율\n<img class='V0NZnDRF UEasJ5rN' width='100%' src='data:image/svg+xml;base64,PHN2ZyB3aWR0aD0iNjQwIiBoZWlnaHQ9IjM2MCIgeG1sbnM9Imh0dHA6Ly93d3cudzMub3JnLzIwMDA"
    },
    {
      "name": "빠른지원: 짙은 안개 강공격",
      "major": "지원스킬",
      "minor": "빠른지원",
      "description": "짙은 안개 강공격\n현재 조작 중인 캐릭터가 넉업되면 을 짧게 탭하여 시전:빠른 지원은 [단상]으로, 시전 시 에테리얼 형상을 재현해 전방의 원형 구역에 낙하 공격을 가하여 에테르 피해를 준다.[꿈세계] 상태가 아닐 때 루시아가 이 [환상]을 시전하면 [꿈세계 게이지] 20pt를 획득한다. 5초 동안 최대 1회 획득할 수 있다.스킬을 시전하는 동안 무적 효과를 보유한다.\n구상 / 합창 / 여진 공격 피해 배율\n구상 / 합창 / 여진 공격 그로기 배율\n<img width='100%' src='data:image/svg+xml;base64,PHN2ZyB3aWR0aD0iNjQwIiBoZWlnaHQ9IjM"
    },
    {
      "name": "패링지원: 환몽의 소리",
      "major": "지원스킬",
      "minor": "패링지원",
      "description": "환몽의 소리\n출전 캐릭터 피격 직전에 을 짧게 탭하여 시전:적의 공격을 패링하고 대량의 그로기 수치를 누적한다.스킬을 시전하는 동안 무적 효과를 보유한다.\n가벼운 패링 그로기 배율\n강한 패링 그로기 배율\n연속 패링 그로기 배율\n<div class='iR1C9VHd' data-"
    },
    {
      "name": "지원돌격: 꿈을 그리는 목소리",
      "major": "지원스킬",
      "minor": "지원돌격",
      "description": "꿈을 그리는 목소리\n[패링/회피 지원] 시전 후 을 짧게 탭하여 시전:지원 돌격은 [합창]으로, 시전 시 에테리얼 형상을 재현해 전방의 원형 구역에 강력한 낙하 공격을 가해 에테르 피해를 준다.[꿈세계] 상태가 아닐 때, 루시아가 이 [합창]을 시전하면 [꿈 게이지] 40pt를 획득한다.스킬을 시전하는 동안 무적 효과를 보유한다.\n<img class='V0NZnDRF UEasJ5rN' width='100%' src='data:image/svg+xml;base64,PHN2ZyB3aWR0aD0iNjQwIiBoZWlnaHQ9IjM2MCIgeG1sbnM9Imh0dHA6Ly93d3cudzMub3JnLzIwMDAvc3ZnIj48L3N2Zz4=' data-filesize='20218283' data-src='//i.namu.wiki/i/EBjwzj6k10709QteoXE9qMWLnWnaWCV00wlHmV99MUCVzi35Ko1_0KXIa9u542i13A89_uNI2UGQ9FwS3NzwuQ.gif' alt='루시아 지원 돌격' data-video-src='//i.namu.wiki/i/0zcDvUahupSrUqFeg7dvdoM725Et_RRoCBVxT7KZUCeMragfSOaiTn3t0s2o"
    },
    {
      "name": "특수스킬: 사신 협주곡·폭풍",
      "major": "특수스킬",
      "minor": "특수스킬",
      "description": "사신 협주곡·폭풍\n을 짧게 탭하여 시전:특수 스킬은 [단상]으로, 시전 시 에테리얼 형상을 재현해 전방 직선 구역에 베기를 시전하여 에테르 피해를 준다.교전 상태이면서 [꿈세계] 상태가 아닐 때, 루시아가 이 [단상]을 시전하면 [꿈세계 게이지] 20pt를 획득한다. 5초 동안 최대 1회 획득할 수 있다.\n구상 / 합창 / 여진 공격 피해 배율\n구상 / 합창 / 여진 공격 그로기 배율\n<img width='100%' src='data:image/svg+xml;base64,PHN2ZyB3aWR0aD0iNjQwIiBoZWlnaHQ9IjM2MCIgeG1sbnM9Imh0dHA6Ly93d3cudzMub3JnLzIwMDAvc3ZnIj48L3N2Zz4=' data-v-f43ef"
    },
    {
      "name": "강화특수스킬: 사신 협주곡·여명",
      "major": "특수스킬",
      "minor": "강화특수스킬",
      "description": "사신 협주곡·여명\n에너지가 충분한 상태에서 을 짧게 탭하여 시전:강화 특수 스킬은 [합창]으로, 시전 시 에테리얼 형상을 재현해 전방 직선 구역에 강력한 베기를 시전하여 에테르 피해를 준다.루시아가 [합창]을 시전하면 파티 내 모든 캐릭터에게 [어둠 돌파] 상태를 부여한다. [어둠 돌파] 상태에서는 관입력이 300pt 증가하며, 루시아의 초기 HP 최대치가 10000을 초과할 때, 초과한 200pt마다 관입력이 추가로 10pt 증가한다. [어둠 돌파] 상태는 최대 900.0pt의 관입력을 증가시킨다. 지속 시간: 20초, 중복 발동 시 지속 시간이 갱신된다.[합창]이 피해를 줄 때, 루시아는 HP 최대치의 n%만큼 마지막 단계 공격의 피해를 추가로 증가시킨다.루시아가 강화 특수 스킬을 시전할 때, 자신이 [꿈세계] 상태이고 [에테르 장막·용천]이 적용 중이라면 [에테르 장막·용천]의 지속 시간이 12초 연장된다.루시아는 강화 특수 스킬을 시전한 후 즉시 [일반 공격] 5단을 이어서 시전할 수 있다.[꿈세계] 상태가 아닐 때 루시아가 이 [합창]을 시전하면 [꿈세계 게이지] 60pt를 획득한다.스킬을 시전하는 동안 무적 효과를 보유한다.\n관입력 추가 증가 최대치\n[합창] 추가 피해 배율\n60pt\n<td style='text-align:cen"
    },
    {
      "name": "콤보스킬: 찬란한 극장",
      "major": "콤보공격",
      "minor": "콤보스킬",
      "description": "찬란한 극장\n[콤보 스킬] 발동 시 해당 캐릭터를 선택해 시전:콤보 스킬은 [합창]으로, 시전 시 에테리얼 형상을 재현해 전방 원형 구역의 적을 끌어당기고 에테르 피해를 준다.[꿈세계] 상태가 아닐 때, 루시아가 이 [합창]을 시전하면 [꿈세계 게이지] 40pt를 획득한다.스킬을 시전하는 동안 무적 효과를 보유한다.\n찬란한 극장\n사냥 시작! / 꿈의 바다로,"
    },
    {
      "name": "궁극기: 돌격, 대갑주!",
      "major": "궁극기",
      "minor": "궁극기",
      "description": "돌격, 대갑주!\n데시벨 레벨 [Maximum] 달성 시 을 짧게 탭하여 시전:궁극기는 [합창]으로, 시전 시 에테리얼 형상을 재현하고 루시아가 올라타 돌진한다. 방향키 홀드로 돌진 방향을 제어할 수 있으며 돌진 시간이 최대 3초까지 연장된다. 돌진 중에는 경직 저항이 증가하고 받는 피해가 40% 감소하며, 루시아는 사망하지 않고 HP가 최대 1까지만 감소한다.돌진이 멈추면 주변의 넓은 범위에 강력한 타격을 가해 에테르 피해를 주고, 스킬이 적 명중 시 [빠른 지원]이 발동되며, [별빛이 모이는 곳]을 남긴다. [별빛이 모이는 곳]은 8초 동안 지속되며, 캐릭터가 [별빛이 모이는 곳]에 있으면 HP 회복 효과를 얻어 초당 루시아 HP 최대치의 n%를 회복한다. 이 회복 효과는 캐릭터가 [별빛이 모이는 곳]을 벗어난 후 4초가 지나거나 퇴장할 때 사라진다.시전 시 루시아가 [꿈세계] 상태이고 [에테르 장막·용천]이 적용 중이라면, [에테르 장막·용천]의 지속 시간이 24초 연장된다.[꿈세계] 상태가 아닐 때 루시아가 이 [합창]을 시전하면 [꿈세계 게이지] 100pt를 획득하며, 이 [합창] 시전 시 자신이 [꿈세계] 상태라면 다음 번에 [꿈세계] 상태에서 벗어날 때 [꿈세계 게이지] 100pt를 획득하고 다시 [꿈세계] 상태에 진입한다. 이 효과는 중복 획득할 수 없다.강력한 타격을 가하는 동안 무적 효과를 보유한다.\n돌진 단일 충돌 / 궁극기 피해 배율\n돌진 단일 충돌 / 궁극기 그로기 배율\n초당 HP 회복 백분율\n<td style='text-align:cent"
    },
    {
      "name": "핵심패시브: 길 잃은 밤의 찬가",
      "major": "핵심스킬",
      "minor": "핵심패시브",
      "description": "길 잃은 밤의 찬가\n전장 진입 시 루시아는 즉시 [꿈세계 게이지] 60pt를 획득하며, [단상] 혹은 [합창] 시전 시 루시아의 [꿈세계 게이지]가 100pt에 도달하고 [꿈세계] 상태가 되며, 동시에 [에테르 장막·용천]이 가동된다.[꿈세계] 상태 진입 시 [빠른 지원]이 발동되며, 동시에 [에테르 장막·용천]이 발동된다.[에테르 장막·용천] 적용 기간 동안 파티 내 모든 캐릭터의 HP 최대치가 5% 증가한다. 지속 시간: 40초, 중복 발동 시 지속 시간이 최대 300초까지 연장된다.루시아가 [꿈세계] 상태일 때 [단상]을 시전하면 [꿈세계 게이지] 25pt를 소모하고 [단상]을 [합창]으로 업그레이드한다.대기 상태일 때 조작 중인 다른 캐릭터의 공격이 적에게 명중하면, 루시아는 [꿈세계 게이지] 25pt를 소모하여 [여진 공격]을 시전하며, 이 [여진 공격]은 [합창]이다. 스킬 업그레이드나 [여진 공격] 발동한 후 6초 동안은 [여진 공격]이 발동되지 않는다.루시아가 스킬 업그레이드나 [여진 공격]을 시전할 때 파티 내 모든 캐릭터에게 [꿈을 맴도는 동요] 상태가 부여된다. [꿈을 맴도는 동요] 상태에서는 캐릭터가 주는 피해가 n% 증가한다. 지속 시간: 12초, 중복 발동 시 지속 시간이 갱신된다.[꿈세계 게이지]가 부족하거나 [에테르 장막]을 벗어나면 루시아는 [꿈세계] 상태에서 벗어난다.\n주는 피해 증가\n-\n기본 에너지 자동 회복 0.12pt 증가\n기본 공격력 25pt 증가\n기본 에너지 자동 회복 0.12pt 증가\n기본 공격력 25pt 증가\n기본 에너지 자동 회복 0.12pt 증가\n기본 공격력 2"
    },
    {
      "name": "추가능력: 장야의 시편",
      "major": "핵심스킬",
      "minor": "추가능력",
      "description": "장야의 시편\n파티에 [명파] 캐릭터 혹은 [격파] 캐릭터가 존재할 시 발동:[어둠 돌파] 상태 부여 시, 추가로 치명타 피해 30% 증가 효과를 제공한다.\n[ 01 ~ 03 활성화 ]\n[ 04 ~ 06 활성화 ]\n<strong da"
    }
  ],
  "extractedAt": "2026-03-29T11:41:21.212Z"
}