{
  "agent": {
    "fullName": "펄크라 페리니",
    "shortName": "페리니",
    "attr": "물리",
    "cls": "격파",
    "faction": "칼리돈의 자손",
    "grade": "S",
    "version": ""
  },
  "skills": [
    {
      "name": "기본공격: 민첩한 타격",
      "major": "일반공격",
      "minor": "기본공격",
      "description": "민첩한 타격\n을 짧게 탭하여 시전:전방을 향해 최대 3단까지 공격을 펼쳐 물리 피해를 준다.\n1단 / 2단 / 3단 피해 배율\n1단 / 2단 / 3단 그로기 배율\n<table class='XHCLabS-' style='background-color:#fff; color:#000; width:100%; border:2px solid #222;' data-dark-style='background-color:#2"
    },
    {
      "name": "차지공격: 도약 타격",
      "major": "일반공격",
      "minor": "차지공격",
      "description": "도약 타격\n을 홀드해 시전:전방으로 뛰어올라 연속 베기로 물리 피해를 준다.\n<img class='V0NZnDRF UEasJ5rN' width='100%' src='data:image/svg+xml;base64,PHN2ZyB3aWR0a"
    },
    {
      "name": "회피: 직립 반사",
      "major": "회피스킬",
      "minor": "회피",
      "description": "직립 반사\n을 짧게 탭하여 시전:빠른 대시로 회피한다.스킬을 시전하는 동안 무적 효과를 보유한다.\n직립 반사"
    },
    {
      "name": "대시공격: 선제공격의 이점",
      "major": "회피스킬",
      "minor": "대시공격",
      "description": "선제공격의 이점\n회피 시 을 짧게 탭하여 시전:전방을 향해 돌진 베기로 물리 피해를 준다.\n<img class='V0NZnDRF UEasJ5rN' width='100%' src='data:image/svg+xml;base64,PHN"
    },
    {
      "name": "회피반격: 철저한 보복",
      "major": "회피스킬",
      "minor": "회피반격",
      "description": "철저한 보복\n[극한 회피] 발동 후 을 짧게 탭하여 시전:전방의 적을 찌르고, 이어서 빠른 베기로 물리 피해를 준다.스킬을 시전하는 동안 무적 효과를 보유한다.\n<img width='100%' src='data:image/svg+xml;base64,PHN2ZyB3aWR0aD0iNjQwIiBoZWlnaHQ9IjM2MCIgeG1sbnM9Imh0dHA6Ly93d3cudzMub3JnLzIwMDAvc3ZnIj48L3N2Zz4=' data-v-"
    },
    {
      "name": "빠른지원: 고용계약·경호 업무",
      "major": "지원스킬",
      "minor": "빠른지원",
      "description": "고용계약·경호 업무\n현재 조작 중인 캐릭터가 넉업되면 을 짧게 탭하여 시전:전방의 적을 찌르고, 이어서 빠른 베기로 물리 피해를 준다.스킬을 시전하는 동안 무적 효과를 보유한다.\n<img width='100%' src='data:image/svg+xml;base64,PHN2ZyB3aWR0aD0iNjQwIiBoZWlnaHQ9IjM2MCIgeG1sbnM9Imh0dHA6Ly93d3cudzMub3JnLzIwMDAvc3ZnIj48L3N2Zz"
    },
    {
      "name": "패링지원: 고용계약·외주 작전",
      "major": "지원스킬",
      "minor": "패링지원",
      "description": "고용계약·외주 작전\n출전 캐릭터 피격 직전에 을 짧게 탭하여 시전:적의 공격을 회피하고 [극한 시야]를 발동한다.스킬을 시전하는 동안 무적 효과를 보유한다.\n고용계약·외주 작전"
    },
    {
      "name": "지원돌격: 별도 요금",
      "major": "지원스킬",
      "minor": "지원돌격",
      "description": "별도 요금\n[회피 지원] 시전 후 을 짧게 탭하여 시전:전방으로 뛰어올라 총으로 사격하여 물리 피해를 준다.스킬 시전 시 [지원 포인트]를 1pt 소모하여 자신이 [사냥꾼의 걸음] 상태에 진입한다.스킬을 시전하는 동안 무적 효과를 보유한다.\n<img width='100%' src='data:image/svg+xml;base64,PHN2ZyB3aWR0aD"
    },
    {
      "name": "특수스킬: 포식의 발톱",
      "major": "특수스킬",
      "minor": "특수스킬",
      "description": "포식의 발톱\n을 짧게 탭하여 시전:전방을 앞뒤로 빠르게 찔러 물리 피해를 준다.스킬을 시전하는 동안 경직 저항 레벨이 증가한다.\n<img class='V0NZnDRF UEasJ5rN' width='100"
    },
    {
      "name": "강화특수스킬: 포식의 발톱·악몽의 엄습",
      "major": "특수스킬",
      "minor": "강화특수스킬",
      "description": "포식의 발톱·악몽의 엄습\n펄크라가 [사냥꾼의 걸음] 상태 진입 후, 파티 내 다른 조작 중인 캐릭터가 시전한 [특수 스킬] 혹은 [강화 특수 스킬] 강공격이 적에게 명중 시 발동:타깃 적을 둘러싸고 빠르게 앞뒤로 찔러 물리 피해를 준다.스킬 시전 후, 파티 내 다른 조작 중인 캐릭터가 시전한 임의의 공격이 적에게 명중 시 펄크라가 공격을 중복 시전한다. 최대 추가 발동: 5회, 마지막 공격은 더욱 강력한 종결의 일격으로 대체된다.스킬을 시전하는 동안 무적 효과를 보유한다.[특수 스킬: 포식의 발톱·악몽의 엄습]은 [여진 공격]이다.\n종결의 일격 피해 배율\n종결의 일격 그로기 배율\n<td style='"
    },
    {
      "name": "강화특수스킬: 포식의 발톱·빠른 걸음",
      "major": "특수스킬",
      "minor": "강화특수스킬",
      "description": "포식의 발톱·빠른 걸음\n에너지가 충분한 상태에서 을 짧게 탭하여 시전:전방을 여러 차례 앞뒤로 찔러 대량의 물리 피해를 준다.스킬을 시전하는 동안 무적 효과를 보유한다.\n60pt\n<span class='gsBPL0KB' style='w"
    },
    {
      "name": "콤보스킬: 안녕, 이건 몰랐지?",
      "major": "콤보공격",
      "minor": "콤보스킬",
      "description": "안녕, 이건 몰랐지?\n[콤보 스킬] 발동 시 해당 캐릭터를 선택해 시전:전방에 차지 사격을 시전해 대량의 물리 피해를 준다.스킬을 시전하는 동안 무적 효과를 보유한다."
    },
    {
      "name": "궁극기: 자, 놀아 볼까?",
      "major": "궁극기",
      "minor": "궁극기",
      "description": "자, 놀아 볼까?\n데시벨 레벨 [Maximum] 달성 시 을 짧게 탭하여 시전:전방 넓은 범위 내 적을 강력하게 사격해 대량의 물리 피해를 준다.스킬을 시전하는 동안 무적 효과를 보유한다.\n<img width='100%' src='data:image/svg+xml;base64,PHN2ZyB3aWR0aD0iNjQwIiBoZWlnaHQ9IjM2MCIgeG1sbnM9Imh0dHA6Ly93d3"
    },
    {
      "name": "핵심패시브: 사냥꾼의 본능",
      "major": "핵심스킬",
      "minor": "핵심패시브",
      "description": "사냥꾼의 본능\n펄크라가 [강화 특수 스킬], [지원 돌격], [콤보 스킬], [궁극기] 시전 시 [사냥꾼의 걸음] 상태에 진입해 자신이 주는 그로기 수치가 n% 증가한다. 지속 시간: 6초. 다른 캐릭터로 교체 후, 펄크라가 여전히 [사냥꾼의 걸음] 상태인 경우, 해당 지속 시간은 다시 펄크라로 교체 시까지 지속된다. [사냥꾼의 걸음] 상태 진입 후, 자신이 현재 조작 중인 캐릭터인 경우, 펄크라의 강공격이 적에게 명중하면 파티 내 이전 캐릭터의 [빠른 지원]을 발동할 수 있다.\n그로기 수치 증가량\n-\n기본 충격력 6pt 증가\n기본 공격력 25pt 증가\n기본 충격력 6pt 증가\n기본 공격력 25pt 증가\n기본 충격력 6pt 증가\n기본 공격력 25pt 증가"
    },
    {
      "name": "추가능력: 비즈니스 파트너",
      "major": "핵심스킬",
      "minor": "추가능력",
      "description": "비즈니스 파트너\n파티에 [강공] 혹은 [명파] 캐릭터 혹은 자신과 진영이 같은 캐릭터가 존재할 시 발동:펄크라가 시전한 [특수 스킬: 포식의 발톱·악몽의 엄습], [강화 특수 스킬], [지원 돌격], [콤보 스킬], [궁극기]가 적에게 명중 시 적에게 [트랩] 효과를 부여한다. 지속 시간: 15초. [트랩] 효과가 부여된 후, 모든 유닛이 시전한 [여진 공격]으로 타깃에게 주는 피해가 30% 증가한다.\n[ 01 ~ 03 활성화 ]\n[ 04 ~ 06 활성화 ]<span class='PmU3luxG' style='"
    }
  ],
  "extractedAt": "2026-03-26T14:28:27.449Z"
}